slashannots/__init__.py
slashannots/gui.py
slashannots/main.py
pdf_slashannots-0.4.0.dist-info/LICENSE
pdf_slashannots-0.4.0.dist-info/METADATA
pdf_slashannots-0.4.0.dist-info/WHEEL
pdf_slashannots-0.4.0.dist-info/entry_points.txt
pdf_slashannots-0.4.0.dist-info/top_level.txt
pdf_slashannots-0.4.0.dist-info/RECORD
