Metadata-Version: 2.1
Name: pdf-slashannots
Version: 0.4.0
Summary: Redact PDF annotation metadata to control disclosure of personal data
Home-page: https://github.com/cburkert/pdf-slashannots
Maintainer: Christian Burkert
Maintainer-email: cs@cburkert.de
License: MIT
Keywords: pdf,annotations,privacy
Classifier: Topic :: Software Development :: Version Control :: Git
Classifier: Programming Language :: Python :: 3
Classifier: Programming Language :: Python :: 3 :: Only
Classifier: Operating System :: OS Independent
Requires-Python: >=3.9
License-File: LICENSE
Requires-Dist: PyPDF2 (>=2.12.1)
